sentimentpredictor/__init__.py
sentimentpredictor/cli.py
sentimentpredictor/fine_tune.py
sentimentpredictor/integration.py
sentimentpredictor/logger.py
sentimentpredictor/model_loader.py
sentimentpredictor/predictor.py
sentimentpredictor/preprocess.py
sentimentpredictor/suppress_tqdm.py
sentimentpredictor/trends.py
sentimentpredictor/utils.py
sentimentpredictor/visualization.py
sentimentpredictor-0.1.3.dist-info/LICENSE
sentimentpredictor-0.1.3.dist-info/METADATA
sentimentpredictor-0.1.3.dist-info/WHEEL
sentimentpredictor-0.1.3.dist-info/entry_points.txt
sentimentpredictor-0.1.3.dist-info/RECORD
