Metadata-Version: 2.1
Name: sentimentpredictor
Version: 0.1.3
Summary: A flexible sentiment analysis predictor package supporting multiple pre-trained models, customizable preprocessing, visualization tools, fine-tuning capabilities, and seamless integration with pandas DataFrames.
Home-page: https://github.com/ankit-aglawe/sentimentpredictor
License: MIT
Keywords: sentiment analysis,text analysis,machine learning,NLP,transformers,data science,pre-trained models,text mining
Author: ankit-aglawe
Author-email: aglawe.ankit@gmail.com
Requires-Python: >=3.9,<4.0
Classifier: License :: OSI Approved :: MIT License
Classifier: Programming Language :: Python :: 3
Classifier: Programming Language :: Python :: 3.9
Classifier: Programming Language :: Python :: 3.10
Classifier: Programming Language :: Python :: 3.11
Classifier: Programming Language :: Python :: 3.12
Requires-Dist: click (>=8.1.7,<9.0.0)
Requires-Dist: matplotlib (>=3.9.0,<4.0.0)
Requires-Dist: numpy (>=1.19.2,<2.0.0)
Requires-Dist: pandas (>=2.2.2,<3.0.0)
Requires-Dist: torch (>=2.3.1,<3.0.0)
Requires-Dist: transformers (>=4.42.3,<5.0.0)
Project-URL: Changelog, https://github.com/ankit-aglawe/sentimentpredictor/releases
Project-URL: Documentation, https://github.com/ankit-aglawe/sentimentpredictor#readme
Project-URL: Repository, https://github.com/ankit-aglawe/sentimentpredictor
Project-URL: Source, https://github.com/ankit-aglawe/sentimentpredictor
Project-URL: Tracker, https://github.com/ankit-aglawe/sentimentpredictor/issues
